health_indices/__init__.py
health_indices/health_indices.py
ezzat223_health_indices-0.0.1.dist-info/entry_points.txt
ezzat223_health_indices-0.0.1.dist-info/METADATA
ezzat223_health_indices-0.0.1.dist-info/WHEEL
ezzat223_health_indices-0.0.1.dist-info/RECORD
