Metadata-Version: 2.1
Name: ezzat223_health_indices
Version: 0.0.1
Summary: A unified collection of health indices and indicators eg: bmi, bai ...
Home-page: https://github.com/jcharistech/health-indices
Keywords: health-indices,health-indicators,bmi,bodymass index,bai,birth-rate,jcharistech
Author: ezzat223
Author-email: ezzat22hegazy@gmail.com
Requires-Python: >=3.11,<4.0
Classifier: License :: OSI Approved :: MIT License
Classifier: Operating System :: OS Independent
Classifier: Programming Language :: Python :: 3
Classifier: Programming Language :: Python :: 3.11
Classifier: Programming Language :: Python :: 3.12
Classifier: Programming Language :: Python :: 3.13
Classifier: Programming Language :: Python :: 3.6
Classifier: Programming Language :: Python :: 3.7
Classifier: Programming Language :: Python :: 3.8
Classifier: Programming Language :: Python :: 3.9
Requires-Dist: bandit (>=1.8.0,<2.0.0)
Requires-Dist: black (>=24.10.0,<25.0.0)
Requires-Dist: fastapi (>=0.115.6,<0.116.0)
Requires-Dist: isort (>=5.13.2,<6.0.0)
Requires-Dist: python-dotenv (>=1.0.1,<2.0.0)
Requires-Dist: radon (>=6.0.1,<7.0.0)
Requires-Dist: uvicorn (>=0.32.1,<0.33.0)
Requires-Dist: vulture (>=2.14,<3.0)
Project-URL: Repository, https://github.com/jcharistech/health-indices
